db/__init__.py
db/base.py
db/database.py
db/repository.py
db_repository-0.0.2.dist-info/METADATA
db_repository-0.0.2.dist-info/WHEEL
db_repository-0.0.2.dist-info/top_level.txt
db_repository-0.0.2.dist-info/RECORD
